agenthub/__init__.py
agenthub/core.py
agenthub/types.py
agenthub/util.py
agenthub/repl/__init__.py
agenthub/repl/repl.py
aiagenthub-0.0.1.dist-info/LICENSE
aiagenthub-0.0.1.dist-info/METADATA
aiagenthub-0.0.1.dist-info/WHEEL
aiagenthub-0.0.1.dist-info/top_level.txt
aiagenthub-0.0.1.dist-info/RECORD
