Metadata-Version: 2.1
Name: aiagenthub
Version: 0.0.1
Summary: A general-purpose multi-agent orchestration framework.
Author-email: Jacob Weiss <jaweiss2305@gmail.com>
Project-URL: homepage, https://github.com/jacobweiss2305/agenthub
Requires-Python: >=3.7
License-File: LICENSE
Requires-Dist: numpy
Requires-Dist: openai >=1.33.0
Requires-Dist: pytest
Requires-Dist: requests
Requires-Dist: tqdm
Requires-Dist: pre-commit
Requires-Dist: instructor
